freedium.py
omnimd_freedium_reader-0.1.4.dist-info/METADATA
omnimd_freedium_reader-0.1.4.dist-info/WHEEL
omnimd_freedium_reader-0.1.4.dist-info/entry_points.txt
omnimd_freedium_reader-0.1.4.dist-info/RECORD
