Metadata-Version: 2.4
Name: omnimd-freedium-reader
Version: 0.1.4
Summary: A plugin for omni-article-markdown to read Freedium content.
Project-URL: Homepage, https://github.com/caol64/omni-article-markdown/tree/main/plugins/omnimd-freedium-reader
Author-email: Lei <caol64@gmail.com>
License-Expression: MIT
Requires-Python: >=3.13
Requires-Dist: playwright==1.57.0
